project/__init__.py
project/parse.py
calendruparser-0.1.0.dist-info/METADATA
calendruparser-0.1.0.dist-info/WHEEL
calendruparser-0.1.0.dist-info/RECORD
